focus_cli/__init__.py
focus_cli/cli.py
focus_cli/goals.py
focus_cli/notes.py
focus_cli/quotes.py
focus_cli/sprint.py
focus_cli/tasks.py
focus_cli/utils.py
focus_cli/data/goals.json
focus_cli/data/notes.json
focus_cli/data/quotes.json
focus_cli/data/sprints.json
focus_cli/data/task.json
focus_cli-1.0.1.dist-info/licenses/LICENSE
focus_cli-1.0.1.dist-info/METADATA
focus_cli-1.0.1.dist-info/WHEEL
focus_cli-1.0.1.dist-info/top_level.txt
focus_cli-1.0.1.dist-info/RECORD
