Metadata-Version: 2.4
Name: focus-cli
Version: 1.0.1
Summary: A powerful CLI tool for developers to boost productivity
Home-page: https://github.com/pygen-labs/focus-cli
Author: PyGen Labs
Author-email: PyGen Labs <pygen.co@gmail.com>
License: MIT License
Requires-Python: >=3.7
License-File: LICENSE
Dynamic: author
Dynamic: home-page
Dynamic: license-file
Dynamic: requires-python
